tdvisu/__init__.py
tdvisu/construct_dpdb_visu.py
tdvisu/dijkstra.py
tdvisu/reader.py
tdvisu/svgjoin.py
tdvisu/utilities.py
tdvisu/version.py
tdvisu/visualization.py
tdvisu/visualization_data.py
tdvisu-1.2.0.dist-info/COPYING
tdvisu-1.2.0.dist-info/LICENSE
tdvisu-1.2.0.dist-info/METADATA
tdvisu-1.2.0.dist-info/WHEEL
tdvisu-1.2.0.dist-info/top_level.txt
tdvisu-1.2.0.dist-info/RECORD
