Metadata-Version: 2.1
Name: tdvisu
Version: 1.2.0
Summary: Visualizing Dynamic Programming on Tree Decompositions.
Home-page: https://github.com/VaeterchenFrost/tdvisu
Author: Martin Röbke
Author-email: martin.roebke@web.de
License: GPLv3
Keywords: graph visualization dynamic-programming msol-solver
Platform: any
Classifier: Development Status :: 4 - Beta
Classifier: Environment :: Console
Classifier: Intended Audience :: Science/Research
Classifier: Intended Audience :: Education
Classifier: Intended Audience :: Developers
Classifier: Operating System :: OS Independent
Classifier: License :: OSI Approved :: GNU General Public License v3 or later (GPLv3+)
Classifier: Programming Language :: Python :: 3
Classifier: Programming Language :: Python :: 3.12
Classifier: Topic :: Scientific/Engineering :: Visualization
Classifier: Topic :: Multimedia :: Graphics :: Presentation
License-File: LICENSE
License-File: COPYING
Requires-Dist: graphviz
Requires-Dist: psycopg[c]
Requires-Dist: python-benedict[xml]
Requires-Dist: PyYAML
Provides-Extra: test
Requires-Dist: hypothesis; extra == "test"
Requires-Dist: pytest; extra == "test"
Requires-Dist: pytest-mock; extra == "test"
